static_downsampler/__init__.py
static_downsampler/create_hgrid_d2.py
static_downsampler/downsample.py
static_downsampler/make_basin_mask_d2.py
static_downsampler/static.py
static_downsampler-0.0.2.data/scripts/create_hgrid_d2.py
static_downsampler-0.0.2.data/scripts/downsample.py
static_downsampler-0.0.2.data/scripts/make_basin_mask_d2.py
static_downsampler-0.0.2.dist-info/LICENSE
static_downsampler-0.0.2.dist-info/METADATA
static_downsampler-0.0.2.dist-info/WHEEL
static_downsampler-0.0.2.dist-info/top_level.txt
static_downsampler-0.0.2.dist-info/RECORD
