Metadata-Version: 2.1
Name: static-downsampler
Version: 0.0.2
Summary: A tool to downsample MOM static files
Home-page: https://github.com/raphaeldussin/static_downsampler
Author: Raphael Dussin
Author-email: raphael.dussin@gmail.com
License: GPLv3
Platform: UNKNOWN
Requires-Dist: numpy
Requires-Dist: xarray
Requires-Dist: dask
Requires-Dist: netCDF4
Requires-Dist: numba
